Workbook
Name R1048900: Sales_Data!$R$1:$R$1

Sheet Sales_Data
A1: Row ID | B1: Order ID | C1: Order Date | D1: Ship Date | E1: Ship Mode | F1: Customer ID | G1: Customer Name | H1: Segment | I1: Country | J1: City | K1: State | L1: Postal Code | M1: Region | N1: Product ID | O1: Category | P1: Sub-Category | Q1: Product Name | R1: Sales | S1: Quantity | T1: Discount | U1: Profit
A2: 1 | B2: CA-2016-152156 | C2: 42682 | D2: 42685 | E2: Second Class | F2: CG-12520 | G2: Claire Gute | H2: Consumer | I2: United States | J2: Henderson | K2: Kentucky | L2: 42420 | M2: South | N2: FUR-BO-10001798 | O2: Furniture | P2: Bookcases | Q2: Bush Somerset Collection Bookcase | R2: 261.96 | S2: 2 | T2: 0 | U2: 41.9136
A3: 2 | B3: CA-2016-152156 | C3: 42682 | D3: 42685 | E3: Second Class | F3: CG-12520 | G3: Claire Gute | H3: Consumer | I3: United States | J3: Henderson | K3: Kentucky | L3: 42420 | M3: South | N3: FUR-CH-10000454 | O3: Furniture | P3: Chairs | Q3: Hon Deluxe Fabric Upholstered Stacking Chairs, Rounded Back | R3: 731.94 | S3: 3 | T3: 0 | U3: 219.582
A4: 3 | B4: CA-2016-138688 | C4: 42533 | D4: 42537 | E4: Second Class | F4: DV-13045 | G4: Darrin Van Huff | H4: Corporate | I4: United States | J4: Los Angeles | K4: California | L4: 90036 | M4: West | N4: OFF-LA-10000240 | O4: Office Supplies | P4: Labels | Q4: Self-Adhesive Address Labels for Typewriters by Universal | R4: 14.62 | S4: 2 | T4: 0 | U4: 6.8714
A5: 4 | B5: US-2015-108966 | C5: 42288 | D5: 42295 | E5: Standard Class | F5: SO-20335 | G5: Sean O'Donnell | H5: Consumer | I5: United States | J5: Fort Lauderdale | K5: Florida | L5: 33311 | M5: South | N5: FUR-TA-10000577 | O5: Furniture | P5: Tables | Q5: Bretford CR4500 Series Slim Rectangular Table | R5: 957.5775 | S5: 5 | T5: 0.45 | U5: -383.031
A6: 5 | B6: US-2015-108966 | C6: 42288 | D6: 42295 | E6: Standard Class | F6: SO-20335 | G6: Sean O'Donnell | H6: Consumer | I6: United States | J6: Fort Lauderdale | K6: Florida | L6: 33311 | M6: South | N6: OFF-ST-10000760 | O6: Office Supplies | P6: Storage | Q6: Eldon Fold 'N Roll Cart System | R6: 22.368 | S6: 2 | T6: 0.2 | U6: 2.5164
A7: 6 | B7: CA-2014-115812 | C7: 41799 | D7: 41804 | E7: Standard Class | F7: BH-11710 | G7: Brosina Hoffman | H7: Consumer | I7: United States | J7: Los Angeles | K7: California | L7: 90032 | M7: West | N7: FUR-FU-10001487 | O7: Furniture | P7: Furnishings | Q7: Eldon Expressions Wood and Plastic Desk Accessories, Cherry Wood | R7: 48.86 | S7: 7 | T7: 0 | U7: 14.1694
A8: 7 | B8: CA-2014-115812 | C8: 41799 | D8: 41804 | E8: Standard Class | F8: BH-11710 | G8: Brosina Hoffman | H8: Consumer | I8: United States | J8: Los Angeles | K8: California | L8: 90032 | M8: West | N8: OFF-AR-10002833 | O8: Office Supplies | P8: Art | Q8: Newell 322 | R8: 7.28 | S8: 4 | T8: 0 | U8: 1.9656
A9: 8 | B9: CA-2014-115812 | C9: 41799 | D9: 41804 | E9: Standard Class | F9: BH-11710 | G9: Brosina Hoffman | H9: Consumer | I9: United States | J9: Los Angeles | K9: California | L9: 90032 | M9: West | N9: TEC-PH-10002275 | O9: Technology | P9: Phones | Q9: Mitel 5320 IP Phone VoIP phone | R9: 907.152 | S9: 6 | T9: 0.2 | U9: 90.7152
A10: 9 | B10: CA-2014-115812 | C10: 41799 | D10: 41804 | E10: Standard Class | F10: BH-11710 | G10: Brosina Hoffman | H10: Consumer | I10: United States | J10: Los Angeles | K10: California | L10: 90032 | M10: West | N10: OFF-BI-10003910 | O10: Office Supplies | P10: Binders | Q10: DXL Angle-View Binders with Locking Rings by Samsill | R10: 18.504 | S10: 3 | T10: 0.2 | U10: 5.7825
A11: 10 | B11: CA-2014-115812 | C11: 41799 | D11: 41804 | E11: Standard Class | F11: BH-11710 | G11: Brosina Hoffman | H11: Consumer | I11: United States | J11: Los Angeles | K11: California | L11: 90032 | M11: West | N11: OFF-AP-10002892 | O11: Office Supplies | P11: Appliances | Q11: Belkin F5C206VTEL 6 Outlet Surge | R11: 114.9 | S11: 5 | T11: 0 | U11: 34.47
A12: 11 | B12: CA-2014-115812 | C12: 41799 | D12: 41804 | E12: Standard Class | F12: BH-11710 | G12: Brosina Hoffman | H12: Consumer | I12: United States | J12: Los Angeles | K12: California | L12: 90032 | M12: West | N12: FUR-TA-10001539 | O12: Furniture | P12: Tables | Q12: Chromcraft Rectangular Conference Tables | R12: 1706.184 | S12: 9 | T12: 0.2 | U12: 85.3092
A13: 12 | B13: CA-2014-115812 | C13: 41799 | D13: 41804 | E13: Standard Class | F13: BH-11710 | G13: Brosina Hoffman | H13: Consumer | I13: United States | J13: Los Angeles | K13: California | L13: 90032 | M13: West | N13: TEC-PH-10002033 | O13: Technology | P13: Phones | Q13: Konftel 250 Conference phone - Charcoal black | R13: 911.424 | S13: 4 | T13: 0.2 | U13: 68.3568
... A9995: 9994 | B9995: CA-2017-119914 | C9995: 42859 | D9995: 42864 | E9995: Second Class | F9995: CC-12220 | G9995: Chris Cortes | H9995: Consumer | I9995: United States | J9995: Westminster | K9995: California | L9995: 92683 | M9995: West | N9995: OFF-AP-10002684 | O9995: Office Supplies | P9995: Appliances | Q9995: Acco 7-Outlet Masterpiece Power Center, Wihtout Fax/Phone Line Protection | R9995: 243.16 | S9995: 2 | T9995: 0 | U9995: 72.948

Sheet Summary
A1: SALES MIS REPORT | C1: REPORT DATE | D1: =TODAY() -> 46322
D2: Category | E2: Sum of Sales | F2: Sum of Profit
A3: TOTAL SALES | B3: =SUM(Sales_Data!R2:R9995) -> 2297200.9 | D3: Furniture | E3: 741999.8 | F3: 18451.273 | I3: CATEGORY PROFITABILITY | J3: Column1 | L3: Category | M3: Sum of Sales | O3: Region | P3: Sum of Sales
A4: UNIQUE ORDERS | B4: =COUNTA(_xlfn.UNIQUE(Sales_Data!B2:B9995)) -> 5009 | D4: Office Supplies | E4: 719047.03 | F4: 122490.8 | I4: CATEGORY | J4: PROFIT MARGIN | L4: Furniture | M4: 741999.8 | O4: Central | P4: 501239.89
A5: TOTAL PROFIT | B5: =SUM(Sales_Data!U2:U9995) -> 286397.02 | D5: Technology | E5: 836154.03 | F5: 145454.95 | I5: FURNITURE | J5: =F3/E3 -> 0.024866951 | L5: Office Supplies | M5: 719047.03 | O5: East | P5: 678781.24
A6: AVERAGE SALES | B6: =AVERAGE(Sales_Data!R2:R9995) -> 229.858 | D6: Grand Total | E6: 2297200.9 | F6: 286397.02 | I6: OFFICE SUPPLIES | J6: =F4/E4 -> 0.17035158 | L6: Technology | M6: 836154.03 | O6: South | P6: 391721.91
A7: MAXIMUM SALES | B7: =MAX(Sales_Data!R2:R9995) -> 22638.48 | I7: TECHNOLOGY | J7: =F5/E5 -> 0.17395712 | O7: West | P7: 725457.82
A8: MINIMUM SALES | B8: =MIN(Sales_Data!R2:R9995) -> 0.444
A9: TOTAL QUANTITY SOLD | B9: =SUM(Sales_Data!S2:S9995) -> 37873
A10: CUSTOMER RECORDS | B10: =COUNTA(Sales_Data!F2:F9995) -> 9994 | D10: Region | E10: Sum of Sales | F10: Sum of Profit | I10: Region | J10: Profit Margin
A11: UNIQUE CUSTOMERS | B11: =COUNTA(_xlfn.UNIQUE(Sales_Data!F2:F9995)) -> 793 | D11: Central | E11: 501239.89 | F11: 39706.362 | I11: Central | J11: =F11/E11 -> 0.079216286
A12: AVERAGE PROFIT | B12: =AVERAGE(Sales_Data!U2:U9995) -> 28.656896 | D12: East | E12: 678781.24 | F12: 91522.78 | I12: East | J12: =F12/E12 -> 0.13483399
A13: PROFIT MARGIN | B13: =B5/B3 -> 0.12467217 | D13: South | E13: 391721.91 | F13: 46749.43 | I13: South | J13: =F13/E13 -> 0.11934342
A14: SALES PERFORMANCE | B14: =IF(B13>=15%,"TARGET ACHIEVED","BELOW TARGET") -> BELOW TARGET | D14: West | E14: 725457.82 | F14: 108418.45 | I14: West | J14: =F14/E14 -> 0.14944831
A15: TARGET GAP | B15: =15%-B13 -> 0.025327828 | D15: Grand Total | E15: 2297200.9 | F15: 286397.02
A16: OVERALL REPORT STATUS | B16: =IF(B13>=15%,"ON TARGET","NEED IMPROVEMENT") -> NEED IMPROVEMENT
A20: KEY BUSINESS INSIGHT
A21: West leads in total sales, total profit, and regional profit margin. Central has the lowest regional profit margin at 7.92%.
A26: BUSINESS OBJECTIVE
A27: Analyze sales and profitability across product categories and regions to identify strong performers and areas for improvement.
A29: PROJECT SUMMARY
A30: Analyze retail sales data using Microsoft Excel to evaluate sales performance, profit margins, product categories, and regional results. Created KPI summaries, PivotTables, and charts to communicate business insights.
